README.rst
setup.py
modellogger/modellogger.py
modellogger.egg-info/PKG-INFO
modellogger.egg-info/SOURCES.txt
modellogger.egg-info/dependency_links.txt
modellogger.egg-info/requires.txt
modellogger.egg-info/top_level.txt
modellogger.egg-info/zip-safe