Metadata-Version: 1.1
Name: modellogger
Version: 0.2.3
Summary: Modelloger is a Python library for storing model's profile and rapid inter model comparision.
Home-page: https://github.com/SohamPathak/modellogger.github.io
Author: SohamPathak
Author-email: sohamkiit636@gmail.com
License: Apache License 2.0
Platform: UNKNOWN
Classifier: Programming Language :: Python :: 3
Classifier: License :: OSI Approved :: Apache Software License
Classifier: Operating System :: OS Independent
Classifier: Development Status :: 3 - Alpha
Classifier: Framework :: Dash
Classifier: Intended Audience :: Developers
